viena/__init__.py
viena/__main__.py
viena/cli.py
viena/config.py
viena/rest_connect.py
viena/t1.py
viena-1.0.1.dist-info/LICENSE.txt
viena-1.0.1.dist-info/METADATA
viena-1.0.1.dist-info/WHEEL
viena-1.0.1.dist-info/entry_points.txt
viena-1.0.1.dist-info/top_level.txt
viena-1.0.1.dist-info/RECORD
