Metadata-Version: 2.1
Name: viena
Version: 1.0.1
Summary: A viena-polygon Python project
Home-page: https://github.com/viena-ai/polygon_python_processes/tree/main/cli-shell-sdk
Author: A. Random Developer
Author-email: author@example.com
Project-URL: Bug Reports, https://github.com/viena-ai/polygon_python_processes/tree/main/cli-shell-sdk/issues
Project-URL: Funding, https://donate.pypi.org
Project-URL: Source, https://github.com/viena-ai/polygon_python_processes/tree/main/cli-shell-sdk/
Keywords: sample,setuptools,development
Classifier: Development Status :: 3 - Alpha
Classifier: Intended Audience :: Developers
Classifier: Topic :: Software Development :: Build Tools
Classifier: License :: OSI Approved :: MIT License
Classifier: Programming Language :: Python :: 3
Classifier: Programming Language :: Python :: 3.7
Classifier: Programming Language :: Python :: 3.6
Classifier: Programming Language :: Python :: 3.8
Classifier: Programming Language :: Python :: 3.9
Classifier: Programming Language :: Python :: 3.10
Classifier: Programming Language :: Python :: 3 :: Only
Requires-Python: >=3.5, <4
License-File: LICENSE.txt
Requires-Dist: awscli
Requires-Dist: typer (==0.3.2)
Requires-Dist: colorama (==0.4.4)
Requires-Dist: shellingham (==1.4.0)
Requires-Dist: pytest (==6.2.4)
Provides-Extra: dev
Requires-Dist: check-manifest ; extra == 'dev'
Provides-Extra: test
Requires-Dist: coverage ; extra == 'test'
